cybox/__init__.py
cybox/compat.py
cybox/helper.py
cybox/version.py
cybox/bindings/__init__.py
cybox/bindings/account_object.py
cybox/bindings/address_object.py
cybox/bindings/api_object.py
cybox/bindings/archive_file_object.py
cybox/bindings/arp_cache_object.py
cybox/bindings/artifact_object.py
cybox/bindings/as_object.py
cybox/bindings/code_object.py
cybox/bindings/custom_object.py
cybox/bindings/cybox_common.py
cybox/bindings/cybox_core.py
cybox/bindings/device_object.py
cybox/bindings/disk_object.py
cybox/bindings/disk_partition_object.py
cybox/bindings/dns_cache_object.py
cybox/bindings/dns_query_object.py
cybox/bindings/dns_record_object.py
cybox/bindings/domain_name_object.py
cybox/bindings/email_message_object.py
cybox/bindings/file_object.py
cybox/bindings/gui_dialogbox_object.py
cybox/bindings/gui_object.py
cybox/bindings/gui_window_object.py
cybox/bindings/hostname_object.py
cybox/bindings/http_session_object.py
cybox/bindings/image_file_object.py
cybox/bindings/library_object.py
cybox/bindings/link_object.py
cybox/bindings/linux_package_object.py
cybox/bindings/memory_object.py
cybox/bindings/mutex_object.py
cybox/bindings/network_connection_object.py
cybox/bindings/network_flow_object.py
cybox/bindings/network_packet_object.py
cybox/bindings/network_route_entry_object.py
cybox/bindings/network_route_object.py
cybox/bindings/network_socket_object.py
cybox/bindings/network_subnet_object.py
cybox/bindings/pdf_file_object.py
cybox/bindings/pipe_object.py
cybox/bindings/port_object.py
cybox/bindings/process_object.py
cybox/bindings/product_object.py
cybox/bindings/semaphore_object.py
cybox/bindings/sms_message_object.py
cybox/bindings/socket_address_object.py
cybox/bindings/system_object.py
cybox/bindings/unix_file_object.py
cybox/bindings/unix_network_route_entry_object.py
cybox/bindings/unix_pipe_object.py
cybox/bindings/unix_process_object.py
cybox/bindings/unix_user_account_object.py
cybox/bindings/unix_volume_object.py
cybox/bindings/uri_object.py
cybox-2.1.0.20.dist-info/LICENSE.txt
cybox-2.1.0.20.dist-info/METADATA
cybox-2.1.0.20.dist-info/WHEEL
cybox-2.1.0.20.dist-info/top_level.txt
cybox-2.1.0.20.dist-info/RECORD
