Metadata-Version: 2.1
Name: cybox
Version: 2.1.0.20
Summary: A Python library for parsing and generating CybOX content.
Home-page: https://cyboxproject.github.io/
Author: CybOX Project, MITRE Corporation
Author-email: cybox@mitre.org
License: BSD
Project-URL: Source Code, https://github.com/CybOXProject/python-cybox/
Project-URL: Documentation, https://cybox.readthedocs.io/
Project-URL: Bug Tracker, https://github.com/CybOXProject/python-cybox/issues/
Platform: UNKNOWN
Classifier: Development Status :: 5 - Production/Stable
Classifier: Intended Audience :: Developers
Classifier: License :: OSI Approved :: BSD License
Classifier: Operating System :: OS Independent
Classifier: Programming Language :: Python :: 2
Classifier: Programming Language :: Python :: 2.7
Classifier: Programming Language :: Python :: 3
Classifier: Programming Language :: Python :: 3.4
Classifier: Programming Language :: Python :: 3.5
Classifier: Programming Language :: Python :: 3.6
Classifier: Programming Language :: Python :: 3.7
Requires-Dist: mixbox (>=1.0.2)
Requires-Dist: python-dateutil
Requires-Dist: lxml (>=2.2.3) ; python_version == "2.7" or python_version >= "3.5"
Requires-Dist: lxml (<4.4.0,>=2.2.3) ; python_version > "2.7" and python_version < "3.5"
